macresources/__init__.py
macresources/binhex.py
macresources/greggybits.py
macresources/instacomp.py
macresources/main.py
macresources-1.2.data/scripts/SimpleDeRez
macresources-1.2.data/scripts/SimpleRez
macresources-1.2.data/scripts/greggybits
macresources-1.2.data/scripts/hexrez
macresources-1.2.data/scripts/instacomp
macresources-1.2.data/scripts/rezhex
macresources-1.2.data/scripts/rfx
macresources-1.2.data/scripts/sortrez
macresources-1.2.dist-info/LICENSE
macresources-1.2.dist-info/METADATA
macresources-1.2.dist-info/WHEEL
macresources-1.2.dist-info/top_level.txt
macresources-1.2.dist-info/RECORD
