Metadata-Version: 2.1
Name: macresources
Version: 1.2
Summary: Library for working with legacy Macintosh resource forks
Home-page: https://github.com/elliotnunn/macresources
Author: Elliot Nunn
Author-email: elliotnunn@me.com
License: MIT
Platform: UNKNOWN
Classifier: Programming Language :: Python :: 3 :: Only
Classifier: Operating System :: OS Independent
Classifier: License :: OSI Approved :: MIT License
Classifier: Topic :: System :: Filesystems
Classifier: Development Status :: 3 - Alpha
